README.md
setup.py
nig/__init__.py
nig/__main__.py
nig/upload.py
nig_upload.egg-info/PKG-INFO
nig_upload.egg-info/SOURCES.txt
nig_upload.egg-info/dependency_links.txt
nig_upload.egg-info/entry_points.txt
nig_upload.egg-info/requires.txt
nig_upload.egg-info/top_level.txt