Metadata-Version: 2.4
Name: nig-upload
Version: 0.4.3
Summary: CLI script for automated uploads of NIG studies
Home-page: 
License: MIT
Classifier: Programming Language :: Python
Classifier: Intended Audience :: Developers
Classifier: Development Status :: 3 - Alpha
Classifier: License :: OSI Approved :: MIT License
Classifier: Programming Language :: Python :: 3.7
Classifier: Programming Language :: Python :: 3.8
Classifier: Programming Language :: Python :: 3.9
Requires-Python: >=3.7.0
Requires-Dist: python-dateutil
Requires-Dist: pytz
Requires-Dist: requests>=2.6.1
Requires-Dist: typer[all]==0.4.0
Requires-Dist: click==8.0.1
Dynamic: classifier
Dynamic: license
Dynamic: requires-dist
Dynamic: requires-python
Dynamic: summary
